cs2_battle_bot_client/__init__.py
cs2_battle_bot_client/api_config.py
cs2_battle_bot_client/models/DiscordUser.py
cs2_battle_bot_client/models/Guild.py
cs2_battle_bot_client/models/Map.py
cs2_battle_bot_client/models/MapBan.py
cs2_battle_bot_client/models/Match.py
cs2_battle_bot_client/models/MatchMapSelected.py
cs2_battle_bot_client/models/Nested.py
cs2_battle_bot_client/models/PaginatedDiscordUserList.py
cs2_battle_bot_client/models/PaginatedGuildList.py
cs2_battle_bot_client/models/PaginatedMapList.py
cs2_battle_bot_client/models/PaginatedMatchList.py
cs2_battle_bot_client/models/PaginatedPlayerList.py
cs2_battle_bot_client/models/PaginatedServerList.py
cs2_battle_bot_client/models/PaginatedSteamUserList.py
cs2_battle_bot_client/models/PaginatedTeamList.py
cs2_battle_bot_client/models/PatchedDiscordUser.py
cs2_battle_bot_client/models/PatchedGuild.py
cs2_battle_bot_client/models/PatchedMap.py
cs2_battle_bot_client/models/PatchedMatch.py
cs2_battle_bot_client/models/PatchedPlayer.py
cs2_battle_bot_client/models/PatchedServer.py
cs2_battle_bot_client/models/PatchedSteamUser.py
cs2_battle_bot_client/models/PatchedTeam.py
cs2_battle_bot_client/models/Player.py
cs2_battle_bot_client/models/Server.py
cs2_battle_bot_client/models/StatusEnum.py
cs2_battle_bot_client/models/SteamUser.py
cs2_battle_bot_client/models/Team.py
cs2_battle_bot_client/models/TypeEnum.py
cs2_battle_bot_client/models/__init__.py
cs2_battle_bot_client/services/__init__.py
cs2_battle_bot_client/services/async_discord_users_service.py
cs2_battle_bot_client/services/async_guilds_service.py
cs2_battle_bot_client/services/async_maps_service.py
cs2_battle_bot_client/services/async_matches_service.py
cs2_battle_bot_client/services/async_players_service.py
cs2_battle_bot_client/services/async_schema_service.py
cs2_battle_bot_client/services/async_servers_service.py
cs2_battle_bot_client/services/async_steam_users_service.py
cs2_battle_bot_client/services/async_teams_service.py
cs2_battle_bot_client-0.0.5.dist-info/METADATA
cs2_battle_bot_client-0.0.5.dist-info/WHEEL
cs2_battle_bot_client-0.0.5.dist-info/RECORD
