Metadata-Version: 2.1
Name: cs2-battle-bot-client
Version: 0.0.5
Summary: 
Author: Adrian Ciolek
Author-email: ciolek.adrian@protonmail.com
Requires-Python: >=3.10,<4.0
Classifier: Programming Language :: Python :: 3
Classifier: Programming Language :: Python :: 3.10
Classifier: Programming Language :: Python :: 3.11
Classifier: Programming Language :: Python :: 3.12
Requires-Dist: openapi-python-generator (>=0.5.0,<0.6.0)
